argo_jupyter_scheduler/__init__.py
argo_jupyter_scheduler/_version.py
argo_jupyter_scheduler/executor.py
argo_jupyter_scheduler/scheduler.py
argo_jupyter_scheduler/task_runner.py
argo_jupyter_scheduler/utils.py
argo_jupyter_scheduler-2024.6.1.dist-info/METADATA
argo_jupyter_scheduler-2024.6.1.dist-info/WHEEL
argo_jupyter_scheduler-2024.6.1.dist-info/licenses/LICENSE.txt
argo_jupyter_scheduler-2024.6.1.dist-info/RECORD
