Metadata-Version: 2.3
Name: argo-jupyter-scheduler
Version: 2024.6.1
Summary: Argo-Workflow backend extension for Jupyter-Scheduler.
Project-URL: Documentation, https://github.com/nebari-dev/argo-jupyter-scheduler#readme
Project-URL: Issues, https://github.com/nebari-dev/argo-jupyter-scheduler/issues
Project-URL: Source, https://github.com/nebari-dev/argo-jupyter-scheduler
Author-email: iameskild <eeriksen@quansight.com>
License-Expression: MIT
License-File: LICENSE.txt
Classifier: Development Status :: 4 - Beta
Classifier: Programming Language :: Python
Classifier: Programming Language :: Python :: 3.8
Classifier: Programming Language :: Python :: 3.9
Classifier: Programming Language :: Python :: 3.10
Classifier: Programming Language :: Python :: 3.11
Classifier: Programming Language :: Python :: Implementation :: PyPy
Requires-Python: >=3.7
Requires-Dist: hera-workflows
Requires-Dist: jupyter-scheduler
Requires-Dist: jupyter-server
Requires-Dist: psutil
Requires-Dist: traitlets
Requires-Dist: urllib3
Provides-Extra: dev
Requires-Dist: black; extra == 'dev'
Requires-Dist: isort; extra == 'dev'
Requires-Dist: jupyter-server[test]<3,>=1.6; extra == 'dev'
Requires-Dist: pre-commit; extra == 'dev'
Requires-Dist: pytest; extra == 'dev'
Requires-Dist: pytest-cov; extra == 'dev'
Requires-Dist: ruff; extra == 'dev'
